pipelines_declarative_executor/__init__.py
pipelines_declarative_executor/__main__.py
pipelines_declarative_executor/executor/condition_processor.py
pipelines_declarative_executor/executor/context_files_processor.py
pipelines_declarative_executor/executor/params_processor.py
pipelines_declarative_executor/executor/pipeline_executor.py
pipelines_declarative_executor/executor/stage_processor.py
pipelines_declarative_executor/model/exceptions.py
pipelines_declarative_executor/model/pipeline.py
pipelines_declarative_executor/model/report.py
pipelines_declarative_executor/model/stage.py
pipelines_declarative_executor/orchestrator/pipeline_orchestrator.py
pipelines_declarative_executor/orchestrator/retry_orchestrator.py
pipelines_declarative_executor/report/report_collector.py
pipelines_declarative_executor/report/report_summary_table.py
pipelines_declarative_executor/report/report_uploader.py
pipelines_declarative_executor/utils/archive_utils.py
pipelines_declarative_executor/utils/auth_utils.py
pipelines_declarative_executor/utils/common_utils.py
pipelines_declarative_executor/utils/constants.py
pipelines_declarative_executor/utils/debug_data_collector.py
pipelines_declarative_executor/utils/env_var_utils.py
pipelines_declarative_executor/utils/logging_utils.py
pipelines_declarative_executor/utils/sops_utils.py
pipelines_declarative_executor/utils/string_utils.py
pipelines_declarative_executor/x_modules_ops/dict_utils.py
pipelines_declarative_executor/x_modules_ops/job_data_registry.py
qubership_pipelines_declarative_executor-2.0.2.dist-info/METADATA
qubership_pipelines_declarative_executor-2.0.2.dist-info/WHEEL
qubership_pipelines_declarative_executor-2.0.2.dist-info/entry_points.txt
qubership_pipelines_declarative_executor-2.0.2.dist-info/licenses/LICENSE
qubership_pipelines_declarative_executor-2.0.2.dist-info/RECORD
