Metadata-Version: 2.4
Name: qubership-pipelines-declarative-executor
Version: 2.0.2
Summary: Qubership Pipelines Declarative Executor
License: Apache-2.0
License-File: LICENSE
Author: Qubership
Requires-Python: >=3.11,<4.0
Classifier: License :: OSI Approved :: Apache Software License
Classifier: Programming Language :: Python :: 3
Classifier: Programming Language :: Python :: 3.11
Classifier: Programming Language :: Python :: 3.12
Classifier: Programming Language :: Python :: 3.13
Classifier: Programming Language :: Python :: 3.14
Requires-Dist: PyYAML (>=6.0,<7.0)
Requires-Dist: aiofiles (>=24.1.0,<25.0.0)
Requires-Dist: aiohttp (>=3.12.15,<4.0.0)
Requires-Dist: click (>=8.1,<9.0)
Requires-Dist: miniopy-async (>=1.23.4,<2.0.0)
Requires-Dist: requests (>=2.32.3,<3.0.0)
Requires-Dist: tabulate (==0.9.0)
